foliant/cli/bump.py
foliantcontrib.bump-1.0.2.dist-info/METADATA
foliantcontrib.bump-1.0.2.dist-info/RECORD
foliantcontrib.bump-1.0.2.dist-info/WHEEL
foliantcontrib.bump-1.0.2.dist-info/top_level.txt
