Metadata-Version: 2.1
Name: foliantcontrib.bump
Version: 1.0.2
Summary: Version bumper for Foliant projects.
Home-page: https://github.com/foliant-docs/foliantcontrib.bump
Author: Konstantin Molchanov
Author-email: moigagoo@live.com
License: MIT
Platform: any
Classifier: Development Status :: 5 - Production/Stable
Classifier: Environment :: Console
Classifier: Intended Audience :: Developers
Classifier: License :: OSI Approved :: MIT License
Classifier: Operating System :: OS Independent
Classifier: Programming Language :: Python
Classifier: Topic :: Documentation
Classifier: Topic :: Utilities
Requires-Dist: foliant (>=1.0.4)
Requires-Dist: semver
